homog/__init__.py
homog/homog.py
homog/quat.py
homog/sym.py
homog-0.1.12.dist-info/DESCRIPTION.rst
homog-0.1.12.dist-info/METADATA
homog-0.1.12.dist-info/RECORD
homog-0.1.12.dist-info/WHEEL
homog-0.1.12.dist-info/metadata.json
homog-0.1.12.dist-info/top_level.txt
